src/aipolabs_mcp/__init__.py
src/aipolabs_mcp/__main__.py
src/aipolabs_mcp/apps_server.py
src/aipolabs_mcp/unified_server.py
src/aipolabs_mcp/common/__init__.py
src/aipolabs_mcp/common/runners.py
src/aipolabs_mcp/common/validators.py
mseep_aipolabs_mcp-0.0.1b5.dist-info/METADATA
mseep_aipolabs_mcp-0.0.1b5.dist-info/WHEEL
mseep_aipolabs_mcp-0.0.1b5.dist-info/entry_points.txt
mseep_aipolabs_mcp-0.0.1b5.dist-info/licenses/LICENSE
mseep_aipolabs_mcp-0.0.1b5.dist-info/RECORD
