Metadata-Version: 2.4
Name: mseep-aipolabs-mcp
Version: 0.0.1b5
Summary: Aipolabs MCP server, built on top of ACI.dev
Author-email: Aipolabs <support@aipolabs.xyz>
Maintainer-email: hanyi <support@aipolabs.xyz>
License-File: LICENSE
Keywords: aci,aipolabs,function calling,llm,mcp,mcp server,tool calling
Classifier: Development Status :: 4 - Beta
Classifier: Intended Audience :: Developers
Classifier: Operating System :: MacOS
Classifier: Operating System :: Microsoft :: Windows
Classifier: Operating System :: OS Independent
Classifier: Operating System :: POSIX
Classifier: Operating System :: POSIX :: Linux
Classifier: Programming Language :: Python :: 3.10
Classifier: Programming Language :: Python :: 3.11
Classifier: Programming Language :: Python :: 3.12
Classifier: Programming Language :: Python :: 3.13
Classifier: Topic :: Software Development :: Libraries :: Python Modules
Classifier: Typing :: Typed
Requires-Python: >=3.10
Requires-Dist: aipolabs>=0.0.1b7
Requires-Dist: anthropic>=0.49.0
Requires-Dist: anyio>=4.9.0
Requires-Dist: click>=8.1.8
Requires-Dist: mcp>=1.4.1
Requires-Dist: starlette>=0.46.1
Requires-Dist: uvicorn>=0.34.0
